maximalexer/__init__.py
maximalexer/maximalexer.py
maximalexer-1.0.dist-info/DESCRIPTION.rst
maximalexer-1.0.dist-info/METADATA
maximalexer-1.0.dist-info/RECORD
maximalexer-1.0.dist-info/WHEEL
maximalexer-1.0.dist-info/entry_points.txt
maximalexer-1.0.dist-info/metadata.json
maximalexer-1.0.dist-info/top_level.txt
