Metadata-Version: 2.0
Name: maximalexer
Version: 1.0
Summary: A pygments lexer for Maxima (CAS) Code, based on asymptote lexer :)
Home-page: https://github.com/foamscience/maximalexer/
Author: F.M.Elwardi
Author-email: elwardifadeli@gmail.com
License: MIT
Keywords: maxima cas algebra lisp pygment plugins
Platform: UNKNOWN
Classifier: Development Status :: 4 - Beta
Classifier: Intended Audience :: Science/Research
Classifier: Topic :: Text Processing :: Filters
Classifier: License :: OSI Approved :: MIT License
Classifier: Programming Language :: Python :: 2
Classifier: Programming Language :: Python :: 2.6
Classifier: Programming Language :: Python :: 2.7
Classifier: Programming Language :: Python :: 3
Classifier: Programming Language :: Python :: 3.2
Classifier: Programming Language :: Python :: 3.3
Classifier: Programming Language :: Python :: 3.4
